documentdb_mcp/__init__.py
documentdb_mcp/__main__.py
documentdb_mcp/documentdb_agent.py
documentdb_mcp/documentdb_mcp.py
documentdb_mcp/mcp_config.json
documentdb_mcp/middlewares.py
documentdb_mcp/utils.py
documentdb_mcp/skills/documentdb-mcp-analysis/SKILL.md
documentdb_mcp/skills/documentdb-mcp-collections/SKILL.md
documentdb_mcp/skills/documentdb-mcp-crud/SKILL.md
documentdb_mcp/skills/documentdb-mcp-system/SKILL.md
documentdb_mcp/skills/documentdb-mcp-users/SKILL.md
documentdb_mcp-0.0.17.dist-info/licenses/LICENSE
documentdb_mcp-0.0.17.dist-info/METADATA
documentdb_mcp-0.0.17.dist-info/WHEEL
documentdb_mcp-0.0.17.dist-info/entry_points.txt
documentdb_mcp-0.0.17.dist-info/top_level.txt
documentdb_mcp-0.0.17.dist-info/RECORD
